suef_simpletcp/BaseConnection.py
suef_simpletcp/Client.py
suef_simpletcp/Server.py
suef_simpletcp/__init__.py
suef_simpletcp-0.0.4.dist-info/LICENSE
suef_simpletcp-0.0.4.dist-info/METADATA
suef_simpletcp-0.0.4.dist-info/WHEEL
suef_simpletcp-0.0.4.dist-info/top_level.txt
suef_simpletcp-0.0.4.dist-info/RECORD
